clsprop/__init__.py
clsprop/py.typed
clsprop-1.3.1.dist-info/METADATA
clsprop-1.3.1.dist-info/WHEEL
clsprop-1.3.1.dist-info/RECORD
